emr_serverless_customauth/__init__.py
emr_serverless_customauth/customauthenticator.py
emr_serverless_customauth-1.0.1.dist-info/LICENSE.md
emr_serverless_customauth-1.0.1.dist-info/METADATA
emr_serverless_customauth-1.0.1.dist-info/NOTICE.md
emr_serverless_customauth-1.0.1.dist-info/WHEEL
emr_serverless_customauth-1.0.1.dist-info/top_level.txt
emr_serverless_customauth-1.0.1.dist-info/RECORD
