Metadata-Version: 2.1
Name: emr-serverless-customauth
Version: 1.0.1
Summary: EMR Serverless Custom Authenticator for spark magic kernel.
Author-email: EMR Serverless <emr-serverless-dev@amazon.com>
License: 
Keywords: emr-serverless,sparkmagic,custom-auth
Classifier: Development Status :: 4 - Beta
Classifier: Programming Language :: Python :: 3
Requires-Python: >=3.7
License-File: LICENSE.md
License-File: NOTICE.md
Requires-Dist: boto3
